ModelHub/BERT.py
auto_widgets/Chained_drop_down_jupyter.py
auto_widgets/ProgressBar.py
auto_widgets/__init__.py
auto_widgets/feature_group.py
aws_gdrive/DownloadFromGoogleDrive.py
aws_gdrive/DownloadFromS3.py
data_process/ResamplingData.py
data_process/__init__.py
func_decorators/__init__.py
func_decorators/decorators.py
hyperparam_tuning/Tuning.py
hyperparam_tuning/__init__.py
model_trainingtime_prediction/NewPipeline.py
model_trainingtime_prediction/__init__.py
model_trainingtime_prediction/env_detect.py
model_trainingtime_prediction/layer_level_utils.py
model_trainingtime_prediction/model_level_utils.py
model_trainingtime_prediction/model_level_utils_bidirectional_rnn.py
model_trainingtime_prediction/model_level_utils_cnn.py
model_trainingtime_prediction/model_level_utils_rnn.py
model_trainingtime_prediction/pytorch_model_level_dense.py
model_trainingtime_prediction/test.py
model_trainingtime_prediction/train_time_predict.py
model_trainingtime_prediction/data/trainpredict.json
nlp_utils/EmbeddingCNNpredict.py
nlp_utils/EmbeddingRNNpredict.py
nlp_utils/FASTTEXTpredict.py
nlp_utils/LatentDirichletAllocationClass.py
nlp_utils/NBpredict.py
nlp_utils/ONEHOTNNpredict.py
nlp_utils/TFIDFNB.py
nlp_utils/TFIDFpredict.py
nlp_utils/TextProcess.py
nlp_utils/__init__.py
object_detect/box_image_text.py
object_detect/convert_detection_image_to_classification_image.py
object_detect/convert_xml_label_to_txt.py
object_detect/cut_target_object.py
object_detect/generate_masks.py
object_detect/metrics.py
object_detect/paddleMetrics.py
object_detect/xml2json.py
raise_error/__init__.py
raise_error/raise_error_class.py
time_series/TimeSeriesFeatureEngineer.py
time_series/__init__.py
xin_util/AccessSQL.py
xin_util/BarPlots.py
xin_util/CreateDIYdictFromDataFrame.py
xin_util/Euclidean_vectors.py
xin_util/Networkgraph.py
xin_util/NormalizeDistribution.py
xin_util/Optimization.py
xin_util/Plotly_Plot.py
xin_util/PrettyPrintDict.py
xin_util/Quick_autoencoder.py
xin_util/Rank_top_n.py
xin_util-1.4.47.dist-info/LICENSE
xin_util-1.4.47.dist-info/METADATA
xin_util-1.4.47.dist-info/WHEEL
xin_util-1.4.47.dist-info/top_level.txt
xin_util-1.4.47.dist-info/RECORD
