Metadata-Version: 2.1
Name: xin-util
Version: 1.4.47
Summary: Xin's self created helper functions
Home-page: https://github.com/XINZHANG-ops/OwnUtilities
Author: Xin Zhang
Author-email: 1528371521zx@gmail.com
License: MIT
Platform: UNKNOWN
Classifier: Programming Language :: Python :: 3
Classifier: License :: OSI Approved :: MIT License
Classifier: Operating System :: OS Independent
License-File: LICENSE
